Metadata-Version: 2.1
Name: spellmatch
Version: 0.1.0
Summary: Spatial cell representation matching
Home-page: https://github.com/BodenmillerGroup/spellmatch
Author: Jonas Windhager
Author-email: jonas.windhager@uzh.ch
License: MIT
Classifier: Intended Audience :: Science/Research
Classifier: License :: OSI Approved :: MIT License
Classifier: Operating System :: OS Independent
Classifier: Programming Language :: Python
Classifier: Programming Language :: Python :: 3
Classifier: Programming Language :: Python :: 3.9
Classifier: Topic :: Scientific/Engineering :: Bio-Informatics
Classifier: Topic :: Scientific/Engineering :: Image Processing
Requires-Python: <3.10,>=3.9
License-File: LICENSE
Requires-Dist: click
Requires-Dist: click-log
Requires-Dist: napari[all] (>=0.4.15)
Requires-Dist: numpy
Requires-Dist: opencv-python-headless
Requires-Dist: pandas
Requires-Dist: pluggy
Requires-Dist: probreg
Requires-Dist: pydantic
Requires-Dist: pyqtgraph
Requires-Dist: PyYaml
Requires-Dist: qtpy
Requires-Dist: scikit-image (>=0.19.0)
Requires-Dist: scikit-learn
Requires-Dist: scipy (>=1.8.0)
Requires-Dist: shapely
Requires-Dist: SimpleITK
Requires-Dist: tifffile
Requires-Dist: xarray
Provides-Extra: cuda
Requires-Dist: cupy ; extra == 'cuda'
Provides-Extra: nonfree
Requires-Dist: opencv-contrib-python-headless ; extra == 'nonfree'
